simple_calculator_muharram_nizar/__init__.py
simple_calculator_muharram_nizar/calc.py
simple_calculator_muharram_nizar/grammar.py
simple_calculator_muharram_nizar-0.1.0.dist-info/METADATA
simple_calculator_muharram_nizar-0.1.0.dist-info/WHEEL
simple_calculator_muharram_nizar-0.1.0.dist-info/top_level.txt
simple_calculator_muharram_nizar-0.1.0.dist-info/RECORD
